{
  "backup": {
    "github": {
      "accessToken": "",
      "base": "main",
      "head": "main",
      "owner": "",
      "repo": ""
    }
  },
  "debug": false,
  "dividends": {
    "fetchDividend": ["trading212.com", "investing.com", "dividendmax.com"]
  },
  "instruments": {
    "fetchWithIsin": ["trading212.com", "investing.com"],
    "fetchWithSymbol": ["trading212.com"]
  },
  "redis": {
    "ttl": 86400
  },
  "server": {
    "apiLimit": {
      "banAfterMaxHttp429Responses": 30,
      "maxRequestsPerMinute": 300
    },
    "authKey": "",
    "port": 3000
  },
  "suppliers": {
    "finki.io": {
      "key": ""
    }
  }
}
